README.txt
setup.py
ArcRstats.egg-info/PKG-INFO
ArcRstats.egg-info/SOURCES.txt
ArcRstats.egg-info/top_level.txt
arc_r/ArcRstats_0.py
arc_r/ArcRstats_1.py
arc_r/__init__.py
arc_r/check_software.py
arc_r/config.py
arc_r/multivariate_regression.py
arc_r/random_sample.py
