Metadata-Version: 1.0
Name: ArcRstats
Version: 0.8.alpha
Summary: geostatistical functions linking ESRI ArcGIS to R statistics packages
Home-page: http://www.env.duke.edu/geospatial/software/
Author: Ben Best
Author-email: bbest@duke.edu
License: GNU
Keywords: GIS,geographical information systems; statistics; R; GLM,generalized linear model; CART,classification and regression trees; GAM,generalized additive model; connectivity; graph theory; landscape ecology; conservation biology
Platform: UNKNOWN
Classifier: Development Status :: 3 - Alpha
Classifier: Intended Audience :: Science/Research
Classifier: License :: OSI Approved :: GNU General Public License (GPL)
Classifier: Natural Language :: English
Classifier: Operating System :: Microsoft
Classifier: Programming Language :: Python
Classifier: Topic :: Scientific/Engineering :: GIS
Classifier: Topic :: Scientific/Engineering :: Bio-Informatics
Classifier: Topic :: Scientific/Engineering :: Information Analysis
Classifier: Topic :: Scientific/Engineering :: Mathematics
